demomarlib/__init__.py
demomarlib/tokenize.py
demomarlib-0.0.3.dist-info/LICENSE.txt
demomarlib-0.0.3.dist-info/METADATA
demomarlib-0.0.3.dist-info/WHEEL
demomarlib-0.0.3.dist-info/top_level.txt
demomarlib-0.0.3.dist-info/RECORD
