Metadata-Version: 2.1
Name: demomarlib
Version: 0.0.3
Summary: An NLP Library for Marathi Language
Home-page: https://github.com/l3cube-pune/MarathiNLP.git
Author: L3Cube
Author-email: l3cube@gmail.com
License: UNKNOWN
Platform: UNKNOWN
Classifier: Programming Language :: Python :: 3
Classifier: License :: OSI Approved :: MIT License
Classifier: Operating System :: OS Independent
